stactools/browse/Dockerfile-node
stactools/browse/Dockerfile-titiler
stactools/browse/__init__.py
stactools/browse/commands.py
stactools/browse/docker-compose.yml.template
stactools_browse-0.1.7.dist-info/LICENSE
stactools_browse-0.1.7.dist-info/METADATA
stactools_browse-0.1.7.dist-info/WHEEL
stactools_browse-0.1.7.dist-info/top_level.txt
stactools_browse-0.1.7.dist-info/RECORD
