Metadata-Version: 2.1
Name: stactools-browse
Version: 0.1.7
Summary: PROVIDE DESCRIPTION HERE
Home-page: https://github.com/stactools-browses/stactools-browse
Author: stac-utils
Author-email: stac@radiant.earth
License: UNKNOWN
Project-URL: Documentation, https://stactools-browse.readthedocs.io/en/latest/
Project-URL: Issues, https://github.com/stactools-browses/stactools-browse/issues
Keywords: stactools,pystac,catalog,STAC
Platform: UNKNOWN
Classifier: Development Status :: 4 - Beta
Classifier: License :: OSI Approved :: Apache Software License
Classifier: Programming Language :: Python :: 3.6
Classifier: Programming Language :: Python :: 3.7
Classifier: Programming Language :: Python :: 3.8
Classifier: Programming Language :: Python :: 3.9
License-File: LICENSE
Requires-Dist: stactools (>=0.2.6)
Requires-Dist: jinja2 (>=3.0)
